data_handle/00_dividing.py
data_handle/01_las2pcd.py
data_handle/02_pcd2bin.py
data_handle/03_VectorCutting.py
data_handle/04_changeIntenserty.py
data_handle/04_removeLimited.py
data_handle/05_move_position.py
data_handle/07_get_extreme_value.py
data_handle/08_createMydata.py
data_handle/09_create_val_gt.py
data_handle/10_update_z.py
data_handle/11_moveback.py
data_handle/12_json2shp.py
data_handle/12_mergeGEO.py
data_handle/13_bin2pcd.py
data_handle/14_pcd2las.py
data_handle/15_addZ.py
data_handle/16_removeDensity.py
data_handle/__init__.py
data_handle/addZ.py
data_handle/checkerror.py
data_handle/delete_distraction.py
data_handle/mergeFloder.py
data_handle/removeError.py
data_handle/shp2json.py
maptrDH-0.1.0.dist-info/METADATA
maptrDH-0.1.0.dist-info/WHEEL
maptrDH-0.1.0.dist-info/top_level.txt
maptrDH-0.1.0.dist-info/RECORD
