Metadata-Version: 2.1
Name: maptrDH
Version: 0.1.0
Summary: A library for data handling with various utilities.
Home-page: https://github.com/wisdom1python/maptr_dataHandle
Author: Feng XY
Author-email: feng452141@163.com
License: UNKNOWN
Platform: UNKNOWN
Classifier: Programming Language :: Python :: 3
Classifier: License :: OSI Approved :: MIT License
Classifier: Operating System :: OS Independent
Requires-Python: >=3.8
Requires-Dist: geopandas ==0.13.2
Requires-Dist: laspy ==2.5.4
Requires-Dist: matplotlib ==3.5.2
Requires-Dist: numpy ==1.22.2
Requires-Dist: open3d ==0.18.0
Requires-Dist: pandas ==1.4.4
Requires-Dist: pypcd ==0.1.1
Requires-Dist: pyshp ==2.3.1
Requires-Dist: scipy ==1.10.1
Requires-Dist: Shapely ==1.8.5.post1
Requires-Dist: tqdm ==4.66.1
